cabrillo_decoder/__init__.py
cabrillo_decoder/decoder.py
cabrillo_decoder-22.0.1.dist-info/LICENSE
cabrillo_decoder-22.0.1.dist-info/METADATA
cabrillo_decoder-22.0.1.dist-info/WHEEL
cabrillo_decoder-22.0.1.dist-info/top_level.txt
cabrillo_decoder-22.0.1.dist-info/RECORD
